doidownloader/__init__.py
doidownloader/__main__.py
doidownloader/crawl_delays.py
doidownloader/db.py
doidownloader/doidownloader.py
doidownloader/files.py
doidownloader/html.py
doidownloader-0.1.0.dist-info/licenses/LICENSE
doidownloader-0.1.0.dist-info/WHEEL
doidownloader-0.1.0.dist-info/METADATA
doidownloader-0.1.0.dist-info/RECORD
