Metadata-Version: 2.4
Name: doidownloader
Version: 0.1.0
Summary: DOIdownloader: You give it DOIs, it gives you the article PDFs.
Author-email: Raf Guns <raf.guns@uantwerpen.be>
Requires-Python: >=3.12
Classifier: License :: OSI Approved :: MIT License
License-File: LICENSE
Requires-Dist: click>=8.0
Requires-Dist: httpx>=0.23.3
Requires-Dist: lxml>=4.9.1
Requires-Dist: rich>=12.6
Requires-Dist: cssselect>=1.4
Requires-Dist: pytest >=7.1 ; extra == "dev"
Requires-Dist: pytest-cov ; extra == "dev"
Project-URL: Home, https://github.com/rafguns/doidownloader/
Provides-Extra: dev
